bin/android/libagent.so
bin/android/renef_server
bin/linux/renef
bin/macos-arm64/renef
bin/macos-x64/renef
renef_mcp-0.2.0.dist-info/licenses/LICENSE
src/__init__.py
src/app.py
src/main.py
src/process.py
src/resources/__init__.py
src/resources/techniques/__init__.py
src/resources/techniques/loader.py
src/resources/techniques/ssl_pinning.py
src/techniques/ssl_pinning/README.md
src/techniques/ssl_pinning/advanced_bypass_techniques.md
src/techniques/ssl_pinning/android_native.md
src/techniques/ssl_pinning/certificate_pinning_fundamentals.md
src/techniques/ssl_pinning/cordova_ionic.md
src/techniques/ssl_pinning/detection_anti_tampering.md
src/techniques/ssl_pinning/flutter.md
src/techniques/ssl_pinning/how_ssl_tls_works.md
src/techniques/ssl_pinning/introduction_to_ssl_pinning.md
src/techniques/ssl_pinning/network_security_configuration.md
src/techniques/ssl_pinning/react_native.md
src/techniques/ssl_pinning/summary.md
src/techniques/ssl_pinning/third_party_libraries.md
src/techniques/ssl_pinning/unity.md
src/techniques/ssl_pinning/xamarin.md
src/tools/__init__.py
src/tools/adb/__init__.py
src/tools/adb/adb_current_app.py
src/tools/adb/adb_devices.py
src/tools/adb/adb_list_apps.py
src/tools/adb/adb_root_status.py
src/tools/adb/adb_selinux_disable.py
src/tools/adb/adb_selinux_enable.py
src/tools/adb/adb_selinux_status.py
src/tools/adb/adb_start_app_am.py
src/tools/adb/adb_start_app_monkey.py
src/tools/adb/adb_stop_app_am.py
src/tools/core/__init__.py
src/tools/core/renef_attach.py
src/tools/core/renef_cli_reset.py
src/tools/core/renef_console_log.py
src/tools/core/renef_exec.py
src/tools/core/renef_hard_reset.py
src/tools/core/renef_list_apps.py
src/tools/core/renef_load_script.py
src/tools/core/renef_ping.py
src/tools/core/renef_plugins.py
src/tools/core/renef_spawn.py
src/tools/core/renef_thread_backtrace.py
src/tools/core/renef_thread_id.py
src/tools/core/renef_watch_realtime.py
src/tools/core/renef_zero_copy_multiline_exec.py
src/tools/core/run.py
src/tools/file/__init__.py
renef_mcp-0.2.0.dist-info/METADATA
renef_mcp-0.2.0.dist-info/WHEEL
renef_mcp-0.2.0.dist-info/entry_points.txt
renef_mcp-0.2.0.dist-info/top_level.txt
renef_mcp-0.2.0.dist-info/RECORD
